pysrpm/__init__.py
pysrpm/__main__.py
pysrpm/convert.py
pysrpm/rpm.py
pysrpm/presets/00-base.conf
pysrpm/presets/10-compat.conf
pysrpm/presets/10-sphinx.conf
pysrpm-0.0.11.dist-info/METADATA
pysrpm-0.0.11.dist-info/WHEEL
pysrpm-0.0.11.dist-info/entry_points.txt
pysrpm-0.0.11.dist-info/top_level.txt
pysrpm-0.0.11.dist-info/RECORD
