Metadata-Version: 2.1
Name: pysrpm
Version: 0.0.11
Summary: Convert python source distributions to source RPM (or spec files)
Home-page: https://github.com/Cimbali/pysrpm/
Download-URL: https://github.com/Cimbali/pysrpm/releases/latest
Author: Cimbali
Author-email: me@cimba.li
License: GPL-2.0-or-later
Project-URL: Issues, https://github.com/Cimbali/pysrpm/issues/
Project-URL: Source Code, https://github.com/Cimbali/pysrpm/
Keywords: RPM,spec
Classifier: Development Status :: 4 - Beta
Classifier: Programming Language :: Python
Classifier: License :: OSI Approved :: GNU General Public License v2 or later (GPLv2+)
Requires-Python: >=3.6
Requires-Dist: packaging
Requires-Dist: tomli
Requires-Dist: pep517
Requires-Dist: importlib-module ; python_version < "3.8"
Provides-Extra: lint
Requires-Dist: flake8 ; extra == 'lint'
Requires-Dist: flake8-docstrings ; extra == 'lint'
Provides-Extra: test
Requires-Dist: pytest ; extra == 'test'
